drfreverseproxy
