Metadata-Version: 1.1
Name: drf-reverse-proxy
Version: 1.0.1
Summary: Reverse proxy view for Django Rest Framework
Home-page: https://github.com/danpoland/drf-reverse-proxy
Author: Daniel Poland
Author-email: danpoland84@gmail.com
License: MPL-2.0
Platform: UNKNOWN
Classifier: Development Status :: 5 - Production/Stable
Classifier: Environment :: Web Environment
Classifier: Framework :: Django
Classifier: Intended Audience :: Developers
Classifier: License :: OSI Approved :: Mozilla Public License 2.0 (MPL 2.0)
Classifier: Operating System :: OS Independent
Classifier: Natural Language :: English
Classifier: Programming Language :: Python :: 2.7
Classifier: Programming Language :: Python :: 3.5
Classifier: Topic :: Internet :: WWW/HTTP
